PyRocketSim/__init__.py
PyRocketSim/_rocketSim.cp312-win_amd64.pyd
PyRocketSim/visualization.py
pyrocketsim-1.0.1.dist-info/licenses/LICENSE
pyrocketsim-1.0.1.dist-info/METADATA
pyrocketsim-1.0.1.dist-info/WHEEL
pyrocketsim-1.0.1.dist-info/top_level.txt
pyrocketsim-1.0.1.dist-info/RECORD
